settings_models/__init__.py
settings_models/_combat.py
settings_models/doc.py
settings_models/serialization.py
settings_models/validators.py
settings_models/settings/__init__.py
settings_models/settings/assets.py
settings_models/settings/common.py
settings_models/settings/device_keys.py
settings_models/settings/enforcement.py
settings_models/settings/gate_control.py
settings_models/settings/intercom.py
settings_models/settings/io.py
arivo_settings_models-2.5.2.dist-info/METADATA
arivo_settings_models-2.5.2.dist-info/WHEEL
arivo_settings_models-2.5.2.dist-info/top_level.txt
arivo_settings_models-2.5.2.dist-info/RECORD
