Metadata-Version: 2.4
Name: arivo-settings_models
Version: 2.5.2
Summary: Library for arivo parking system settings definitions and models
Home-page: https://gitlab.com/accessio/onegate/settings-models
Author: ARIVO
Author-email: support@arivo.co
License: "GPL-3",
Keywords: arivo
Classifier: Intended Audience :: Developers
Classifier: Programming Language :: Python
Classifier: Programming Language :: Python :: 3
Requires-Dist: pydantic>=2
Requires-Dist: orjson<4,>=3.4.7
Requires-Dist: python-dateutil>=2.7.2
Dynamic: author
Dynamic: author-email
Dynamic: classifier
Dynamic: description
Dynamic: description-content-type
Dynamic: home-page
Dynamic: keywords
Dynamic: license
Dynamic: requires-dist
Dynamic: summary
